cool_graph_plus/__init__.py
cool_graph_plus/my_calculator.py
cool_graph_plus-0.1.0.dist-info/METADATA
cool_graph_plus-0.1.0.dist-info/WHEEL
cool_graph_plus-0.1.0.dist-info/RECORD
