Metadata-Version: 2.3
Name: cool-graph-plus
Version: 0.1.0
Summary: testing purposes
Author: urasvarolgunes
Author-email: urasvarolgunes@gmail.com
Requires-Python: >=3.10
Classifier: Programming Language :: Python :: 3
Classifier: Programming Language :: Python :: 3.10
Classifier: Programming Language :: Python :: 3.11
Classifier: Programming Language :: Python :: 3.12
Classifier: Programming Language :: Python :: 3.13
Requires-Dist: numpy (>=2.2.4,<3.0.0)
